README.rst
setup.cfg
setup.py
apns_proxy_client/__init__.py
apns_proxy_client/core.py
apns_proxy_client.egg-info/PKG-INFO
apns_proxy_client.egg-info/SOURCES.txt
apns_proxy_client.egg-info/dependency_links.txt
apns_proxy_client.egg-info/requires.txt
apns_proxy_client.egg-info/top_level.txt
tests/__init__.py
tests/test_client.py
tests/test_module.py