Metadata-Version: 1.1
Name: apns-proxy-client
Version: 0.1.0
Summary: Client library for APNs Proxy Server.
Home-page: https://github.com/voyagegroup/apns-proxy-client-py
Author: Takashi Nishibayashi
Author-email: takashi_nishibayashi@voyagegroup.com
License: BSD
Keywords: apns
Platform: any
Classifier: Development Status :: 4 - Beta
Classifier: Topic :: Utilities
Classifier: License :: OSI Approved :: BSD License
Classifier: Operating System :: OS Independent
Classifier: Programming Language :: Python
Classifier: Programming Language :: Python :: 2
Classifier: Programming Language :: Python :: 2.6
Classifier: Programming Language :: Python :: 2.7
